{
  "command": "grep",
  "mutating": false,
  "flags": [
    "--cached",
    "--no-cached",
    "--untracked",
    "--no-untracked",
    "--no-index",
    "--index",
    "--exclude-standard",
    "--no-exclude-standard",
    "--recurse-submodules",
    "--no-recurse-submodules",
    "-a",
    "--text",
    "-I",
    "--textconv",
    "--no-textconv",
    "-i",
    "--ignore-case",
    "-w",
    "--word-regexp",
    "-v",
    "--invert-match",
    "-r",
    "--recursive",
    "--no-recursive",
    "--max-depth=0",
    "--max-depth=1",
    "--max-depth=-1",
    "-E",
    "--extended-regexp",
    "-G",
    "--basic-regexp",
    "-F",
    "--fixed-strings",
    "-P",
    "--perl-regexp",
    "-n",
    "--line-number",
    "--no-line-number",
    "--column",
    "--no-column",
    "-h",
    "-H",
    "--full-name",
    "--no-full-name",
    "-l",
    "--files-with-matches",
    "--name-only",
    "-L",
    "--files-without-match",
    "-z",
    "--null",
    "-o",
    "--only-matching",
    "-c",
    "--count",
    "--color=always",
    "--color=never",
    "--color=auto",
    "--no-color",
    "--break",
    "--no-break",
    "--heading",
    "--no-heading",
    "-p",
    "--show-function",
    "-W",
    "--function-context",
    "-C1",
    "-2",
    "--context=3",
    "-A2",
    "--after-context=1",
    "-B2",
    "--before-context=1",
    "--threads=1",
    "--threads=4",
    "-m1",
    "--max-count=0",
    "--max-count=2",
    "--max-count=-1",
    "-q",
    "--quiet",
    "--no-quiet",
    "--all-match",
    "--no-all-match",
    "--ext-grep",
    "--no-ext-grep"
  ],
  "positionals": [
    "fn",
    "TODO",
    "README",
    "lib",
    "^",
    "[a-z]+",
    "does-not-exist-pattern",
    "",
    "HEAD",
    "main",
    "feature",
    "v0.1.0",
    "v0.2.0",
    "HEAD~1",
    "--",
    "README.md",
    "src/lib.rs",
    "src/",
    "*.rs",
    ":^src",
    "does-not-exist"
  ],
  "shapes": [
    "linear",
    "branched",
    "merged",
    "dirty",
    "conflicted",
    "detached",
    "awkward-paths",
    "submodule"
  ]
}
